pcre2-0.5.3.dist-info/RECORD
pcre2-0.5.3.dist-info/WHEEL
pcre2-0.5.3.dist-info/top_level.txt
pcre2-0.5.3.dist-info/METADATA
pcre2-0.5.3.dist-info/licenses/LICENSE
pcre2/CMakeLists.txt
pcre2/__init__.py
pcre2/_cy.cpython-311-darwin.so
pcre2/pcre2.h
pcre2/_cy.pyx
pcre2/_libpcre2.pxd
pcre2-0.5.3.data/data/CMakeLists.txt
pcre2-0.5.3.data/data/LICENSE
pcre2-0.5.3.data/data/Makefile
pcre2-0.5.3.data/data/pyproject.toml
pcre2-0.5.3.data/data/README.md
pcre2-0.5.3.data/data/setup.py
pcre2-0.5.3.data/data/bin/pcre2grep
pcre2-0.5.3.data/data/bin/pcre2test
pcre2-0.5.3.data/data/bin/pcre2-config
pcre2-0.5.3.data/data/include/pcre2posix.h
pcre2-0.5.3.data/data/include/pcre2.h
pcre2-0.5.3.data/data/requirements/test-requirements.txt
pcre2-0.5.3.data/data/requirements/build-requirements.txt
pcre2-0.5.3.data/data/lib/libpcre2-posix.a
pcre2-0.5.3.data/data/lib/libpcre2-8.a
pcre2-0.5.3.data/data/lib/pkgconfig/libpcre2-posix.pc
pcre2-0.5.3.data/data/lib/pkgconfig/libpcre2-8.pc
pcre2-0.5.3.data/data/lib/cmake/pcre2/pcre2-config-version.cmake
pcre2-0.5.3.data/data/lib/cmake/pcre2/pcre2-targets.cmake
pcre2-0.5.3.data/data/lib/cmake/pcre2/pcre2-config.cmake
pcre2-0.5.3.data/data/lib/cmake/pcre2/pcre2-targets-release.cmake
pcre2-0.5.3.data/data/share/man/man3/pcre2_set_recursion_limit.3
pcre2-0.5.3.data/data/share/man/man3/pcre2syntax.3
pcre2-0.5.3.data/data/share/man/man3/pcre2jit.3
pcre2-0.5.3.data/data/share/man/man3/pcre2demo.3
pcre2-0.5.3.data/data/share/man/man3/pcre2_set_offset_limit.3
pcre2-0.5.3.data/data/share/man/man3/pcre2_match_context_create.3
pcre2-0.5.3.data/data/share/man/man3/pcre2serialize.3
pcre2-0.5.3.data/data/share/man/man3/pcre2_set_bsr.3
pcre2-0.5.3.data/data/share/man/man3/pcre2unicode.3
pcre2-0.5.3.data/data/share/man/man3/pcre2_substring_get_bynumber.3
pcre2-0.5.3.data/data/share/man/man3/pcre2_substring_copy_byname.3
pcre2-0.5.3.data/data/share/man/man3/pcre2api.3
pcre2-0.5.3.data/data/share/man/man3/pcre2_set_parens_nest_limit.3
pcre2-0.5.3.data/data/share/man/man3/pcre2_get_startchar.3
pcre2-0.5.3.data/data/share/man/man3/pcre2limits.3
